metapg/migrations/__init__.py
metapg/migrations/models.py
metapg/migrations/runner.py
metapg/migrations/py.typed
metapg_migrations-0.0.1.dist-info/METADATA
metapg_migrations-0.0.1.dist-info/WHEEL
metapg_migrations-0.0.1.dist-info/RECORD
