Metadata-Version: 2.4
Name: metapg.migrations
Version: 0.0.1
Summary: Raw SQL migrations for PostgreSQL with dependency tracking and rollback support
Project-URL: Homepage, https://github.com/metapg/metapg
Project-URL: Repository, https://github.com/metapg/metapg
Project-URL: Issues, https://github.com/metapg/metapg/issues
Project-URL: Documentation, https://metapg.readthedocs.io/
Author-email: Darwin Monroy <darwin@ideatives.com>
License: MIT
Keywords: database,migrations,postgresql,schema,sql
Classifier: Development Status :: 4 - Beta
Classifier: Framework :: AsyncIO
Classifier: Intended Audience :: Developers
Classifier: License :: OSI Approved :: MIT License
Classifier: Programming Language :: Python :: 3
Classifier: Programming Language :: Python :: 3.11
Classifier: Programming Language :: Python :: 3.12
Classifier: Programming Language :: Python :: 3.13
Classifier: Topic :: Database
Classifier: Topic :: Software Development :: Libraries :: Python Modules
Requires-Python: >=3.11
Requires-Dist: metapg-pool>=0.0.1
Provides-Extra: dev
Requires-Dist: black>=24.0.0; extra == 'dev'
Requires-Dist: mypy>=1.11.0; extra == 'dev'
Requires-Dist: pytest-asyncio>=0.24.0; extra == 'dev'
Requires-Dist: pytest-cov>=5.0.0; extra == 'dev'
Requires-Dist: pytest>=8.0.0; extra == 'dev'
Requires-Dist: ruff>=0.6.0; extra == 'dev'
